escore/__init__.py
escore/_bootstrap.py
escore/bases.py
escore/entry_points.py
escore/exceptions.py
escore/resources.py
escore/utils.py
escore/version.py
escore/core/__init__.py
escore/core/dbconnection.py
escore/core/definitions.py
escore/core/element.py
escore/core/exceptions.py
escore/core/execution.py
escore/core/meta.py
escore/core/mixin.py
escore/core/persistence.py
escore/core/process_manager.py
escore/core/process_services.py
escore/core/run_utils.py
escore/core_ops/__init__.py
escore/core_ops/links/__init__.py
escore/core_ops/links/apply.py
escore/core_ops/links/apply_func.py
escore/core_ops/links/assert_in_ds.py
escore/core_ops/links/break_link.py
escore/core_ops/links/ds_object_deleter.py
escore/core_ops/links/ds_to_ds.py
escore/core_ops/links/event_looper.py
escore/core_ops/links/fork_data_collector.py
escore/core_ops/links/fork_example.py
escore/core_ops/links/hello_world.py
escore/core_ops/links/import_data_store.py
escore/core_ops/links/ipython_embed.py
escore/core_ops/links/line_printer.py
escore/core_ops/links/print_ds.py
escore/core_ops/links/repeat_chain.py
escore/core_ops/links/skip_chain_if_empty.py
escore/core_ops/links/skip_chain_if_present.py
escore/core_ops/links/to_ds_dict.py
escore/logger/__init__.py
escore/logger/_logging.py
escore/templates/__init__.py
escore/templates/notebook_template.ipynb
escore/tutorials/__init__.py
escore/tutorials/esk101_helloworld.py
escore/tutorials/esk102_multiple_chains.py
escore/tutorials/esk103_printdatastore.py
escore/tutorials/esk104_basic_datastore_operations.py
escore/tutorials/esk105_A_dont_store_results.py
escore/tutorials/esk105_B_store_each_chain.py
escore/tutorials/esk105_C_begin_at_chain3.py
escore/tutorials/esk105_datastore_pickling.py
escore/tutorials/esk106_cmdline_options.py
escore/tutorials/esk107_chain_looper.py
escore/tutorials/esk108_eventlooper.py
escore/tutorials/esk108_eventlooper.sh
escore/tutorials/esk108_map.py
escore/tutorials/esk108_reduce.py
Eskapade_Core-1.0.0.dist-info/LICENSE
Eskapade_Core-1.0.0.dist-info/METADATA
Eskapade_Core-1.0.0.dist-info/NOTICE
Eskapade_Core-1.0.0.dist-info/WHEEL
Eskapade_Core-1.0.0.dist-info/entry_points.txt
Eskapade_Core-1.0.0.dist-info/top_level.txt
Eskapade_Core-1.0.0.dist-info/RECORD
