Metadata-Version: 2.1
Name: Eskapade-Core
Version: 1.0.0
Summary: Eskapade modular analytics - core
Home-page: http://eskapade.kave.io
Author: KPMG N.V. The Netherlands
Author-email: kave@kpmg.com
License: UNKNOWN
Platform: UNKNOWN
Requires-Python: >=3.6
Requires-Dist: pendulum (==1.2.5)
Requires-Dist: pytest (>=3.5.0)
Requires-Dist: pytest-pylint (>=0.9.0)
